{
	"name": "SecurityRoom_Cabinets_HitBox4",
	"plugin-id": "Sprite",
	"sid": 236010816531915,
	"isGlobal": false,
	"instanceVariables": [],
	"behaviorTypes": [],
	"effectTypes": [],
	"animations": {
		"items": [
			{
				"frames": [
					{
						"width": 250,
						"height": 250,
						"originX": 0.5,
						"originY": 0.5,
						"originalSource": "",
						"exportFormat": "png",
						"exportQuality": 0.8,
						"imageSpriteId": 8788265,
						"useCollisionPoly": true,
						"imagePoints": [
							{
								"name": "KeySpawn",
								"x": -0.28,
								"y": 0.44
							}
						],
						"duration": 1
					}
				],
				"sid": 738796194455680,
				"name": "Animation 1",
				"isLooping": false,
				"isPingPong": false,
				"repeatCount": 1,
				"repeatTo": 0,
				"speed": 5
			}
		],
		"subfolders": []
	}
}